bopku/__init__.py
bopku/__main__.py
bopku/alembic/env.py
bopku/alembic/README
bopku/alembic/script.py.mako
bopku/alembic/versions/2020_12_29_516eba5a44c9_create_sekolah.py
bopku/config.py
bopku/db.py
bopku/main.py
bopku/models/__init__.py
bopku/models/sekolah.py
bopku/version.py
LICENSE
README.md
bopku-0.1.0.dist-info/LICENSE
bopku-0.1.0.dist-info/WHEEL
bopku-0.1.0.dist-info/METADATA
bopku-0.1.0.dist-info/RECORD
