Metadata-Version: 2.1
Name: bopku
Version: 0.1.0
Summary: Alat bantu administrasi BOP (Bantuan Operasional) Paud.
Home-page: https://dapodix.github.io/bopku/
License: GPLv3
Author: hexatester
Author-email: habibrohman@protonmail.com
Requires-Python: >=3.7,<4.0
Classifier: License :: Other/Proprietary License
Classifier: Programming Language :: Python :: 3
Classifier: Programming Language :: Python :: 3.7
Classifier: Programming Language :: Python :: 3.8
Classifier: Programming Language :: Python :: 3.9
Requires-Dist: SQLAlchemy (>=1.3.22,<2.0.0)
Requires-Dist: alembic (>=1.4.3,<2.0.0)
Requires-Dist: dacite (>=1.6.0,<2.0.0)
Project-URL: Repository, https://github.com/dapodix/bopku
